README.rst
setup.py
upload_to_pypi.py
example/__init__.py
example/master_test.py
example/slavetest.py
pyfly/__init__.py
pyfly/core.py
pyfly/events.py
pyfly/flyrpc.py
pyfly/flystate.py
pyfly/runners.py
pyfly/web.py
pyfly.egg-info/PKG-INFO
pyfly.egg-info/SOURCES.txt
pyfly.egg-info/dependency_links.txt
pyfly.egg-info/requires.txt
pyfly.egg-info/top_level.txt
pyfly.egg-info/zip-safe
test/__init__.py