Metadata-Version: 1.2
Name: pyfly
Version: 1.3.2
Summary: load testing framework
Home-page: https://github.com/seuman/pyfly.git
Author: Yang Lei
Author-email: yl.seu@qq.com
License: MIT
Keywords: load test
Platform: UNKNOWN
Classifier: License :: OSI Approved :: MIT License
Classifier: Programming Language :: Python
Classifier: Programming Language :: Python :: 3
Classifier: Programming Language :: Python :: 3.3
Classifier: Programming Language :: Python :: 3.4
Classifier: Programming Language :: Python :: 3.5
Classifier: Programming Language :: Python :: 3.6
Classifier: Intended Audience :: Developers
Classifier: Operating System :: OS Independent
Requires-Python: >=3
